{
  "$schema": "https://developer.microsoft.com/json-schemas/fabric/item/report/definition/visualContainer/2.8.0/schema.json",
  "name": "148a702d70f684139d14",
  "position": {
    "x": 358.57142857142861,
    "y": 4.2857142857142856,
    "z": 1000,
    "height": 39.991,
    "width": 724.28,
    "tabOrder": 8000
  },
  "visual": {
    "visualType": "textbox",
    "objects": {
      "general": [
        {
          "properties": {
            "paragraphs": [
              {
                "textRuns": [
                  {
                    "value": "O Impacto da Era da IA: Produtividade, Renda e Pessoas",
                    "textStyle": {
                      "fontWeight": "bold",
                      "fontSize": "16pt"
                    }
                  }
                ],
                "horizontalTextAlignment": "center"
              }
            ]
          }
        }
      ]
    },
    "drillFilterOtherVisuals": true
  }
}